MANIFEST.in
setup.cfg
setup.py
pixiegateway/__init__.py
pixiegateway/chartThumbnail.py
pixiegateway/chartsManager.py
pixiegateway/exceptions.py
pixiegateway/managedClient.py
pixiegateway/notebookMgr.py
pixiegateway/pixieGatewayApp.py
pixiegateway/session.py
pixiegateway/utils.py
pixiegateway.egg-info/PKG-INFO
pixiegateway.egg-info/SOURCES.txt
pixiegateway.egg-info/dependency_links.txt
pixiegateway.egg-info/entry_points.txt
pixiegateway.egg-info/not-zip-safe
pixiegateway.egg-info/requires.txt
pixiegateway.egg-info/top_level.txt
pixiegateway/admin/__init__.py
pixiegateway/admin/appController.py
pixiegateway/admin/kernelController.py
pixiegateway/handlers/__init__.py
pixiegateway/handlers/adminHandlers.py
pixiegateway/handlers/handlers.py
pixiegateway/kernel/__init__.py
pixiegateway/kernel/base.py
pixiegateway/kernel/local.py
pixiegateway/kernel/remote.py
pixiegateway/static/favicon.ico
pixiegateway/static/codemirror/codemirror.css
pixiegateway/static/codemirror/codemirror.js
pixiegateway/static/codemirror/addon/display/autorefresh.js
pixiegateway/static/codemirror/addon/display/fullscreen.css
pixiegateway/static/codemirror/addon/display/fullscreen.js
pixiegateway/static/codemirror/addon/display/panel.js
pixiegateway/static/codemirror/addon/display/placeholder.js
pixiegateway/static/codemirror/addon/display/rulers.js
pixiegateway/static/codemirror/python/python.js
pixiegateway/static/requirejs/require.js
pixiegateway/template/embedChart.html
pixiegateway/template/genThumbnail.html
pixiegateway/template/headLinks.html
pixiegateway/template/login.html
pixiegateway/template/logo.html
pixiegateway/template/main.html
pixiegateway/template/showChart.html
pixiegateway/template/admin/adminCSS.html
pixiegateway/template/admin/adminConsole.html
pixiegateway/template/admin/adminLogs.html
pixiegateway/template/admin/adminStats.html
pixiegateway/template/admin/chartsJS.html
pixiegateway/template/admin/chartsList.html
pixiegateway/template/admin/kernelDetails.html
pixiegateway/template/admin/pixieappDetails.html
pixiegateway/template/admin/pixieappList.html
pixiegateway/template/admin/statsJS.html
pixiegateway/tests/__init__.py
pixiegateway/tests/test_chartstorage.py
pixiegateway/tests/test_rewrite.py
