Metadata-Version: 1.0
Name: pixiegateway
Version: 0.8
Summary: Server for sharing PixieDust chart and running PixieApps
Home-page: https://github.com/pixiedust/pixiegateway
Author: David Taieb
Author-email: data38777@gmail.com
License: Apache 2.0
Platform: UNKNOWN
